Metadata-Version: 2.4
Name: crsyspqc
Version: 1.0.0
Summary: Python interface to CryptoSys PQC
Author: David Ireland, DI Management Services Pty Ltd t/a CryptoSys
Project-URL: Homepage, https://www.cryptosys.net/pqc/
Project-URL: Issues, https://www.cryptosys.net/contact/
Classifier: Programming Language :: Python :: 3
Requires-Python: >=3.6
